pyakeneo/__init__.py
pyakeneo/auth.py
pyakeneo/client.py
pyakeneo/interfaces.py
pyakeneo/resources.py
pyakeneo/result.py
pyakeneo/utils.py
pyakeneo-1.1.0.dist-info/LICENCE.txt
pyakeneo-1.1.0.dist-info/METADATA
pyakeneo-1.1.0.dist-info/WHEEL
pyakeneo-1.1.0.dist-info/RECORD
