Metadata-Version: 2.3
Name: pyakeneo
Version: 1.1.0
Summary: Python client for the Akeneo API REST
License: MIT
Author: Kave Tech
Author-email: kavetech@kavehome.com
Requires-Python: >=3.11
Classifier: License :: OSI Approved :: MIT License
Classifier: Programming Language :: Python :: 3
Classifier: Programming Language :: Python :: 3.11
Classifier: Programming Language :: Python :: 3.12
Classifier: Programming Language :: Python :: 3.13
Provides-Extra: dev
Requires-Dist: pytest (>=7.0.0,<8.0.0) ; extra == "dev"
Requires-Dist: requests (>=2.28.2,<3.0.0)
Requires-Dist: sphinx (==1.6.5) ; extra == "dev"
Requires-Dist: structlog (>=22.3.0,<23.0.0)
Requires-Dist: vcrpy (>=4.2.1,<5.0.0) ; extra == "dev"
Requires-Dist: vcrpy-unittest (>=0.1.7,<1.0.0) ; extra == "dev"
Project-URL: Homepage, https://github.com/KaveTech/akeneo_api_client
